cosg/__init__.py
cosg/_plotting.py
cosg/cosg.py
cosg-1.0.3.dist-info/METADATA
cosg-1.0.3.dist-info/WHEEL
cosg-1.0.3.dist-info/licenses/LICENSE
cosg-1.0.3.dist-info/RECORD
