Metadata-Version: 2.4
Name: cosg
Version: 1.0.3
Summary: Accurate and fast cell marker gene identification with COSG
Project-URL: Documentation, https://genecell.github.io/COSG
Project-URL: Source, https://github.com/genecell/COSG
Project-URL: Homepage, https://genecell.github.io/COSG
Author-email: Min Dai <dai@broadinstitute.org>
Maintainer-email: Min Dai <dai@broadinstitute.org>
License: BSD-3-Clause
License-File: LICENSE
Classifier: Development Status :: 3 - Alpha
Classifier: Environment :: Console
Classifier: Framework :: Jupyter
Classifier: Intended Audience :: Developers
Classifier: Intended Audience :: Science/Research
Classifier: Natural Language :: English
Classifier: Operating System :: MacOS :: MacOS X
Classifier: Operating System :: Microsoft :: Windows
Classifier: Operating System :: POSIX :: Linux
Classifier: Programming Language :: Python :: 3
Classifier: Programming Language :: Python :: 3.6
Classifier: Programming Language :: Python :: 3.7
Classifier: Programming Language :: Python :: 3.8
Classifier: Programming Language :: Python :: 3.9
Classifier: Programming Language :: Python :: 3.10
Classifier: Programming Language :: Python :: 3.11
Classifier: Programming Language :: Python :: 3.12
Classifier: Topic :: Scientific/Engineering :: Bio-Informatics
Classifier: Topic :: Scientific/Engineering :: Visualization
Requires-Python: >=3.6
Requires-Dist: anndata>=0.8
Requires-Dist: matplotlib>=3.5.2
Requires-Dist: networkx>=2.8.8
Requires-Dist: numpy>=1.17.0
Requires-Dist: pandas>=0.21
Requires-Dist: scanpy>=1.6.0
Requires-Dist: scikit-learn>=0.21.2
Requires-Dist: scipy>=1.4
Requires-Dist: typing-extensions
Provides-Extra: dev
Requires-Dist: pre-commit; extra == 'dev'
